tiny_taskbot/__init__.py
tiny_taskbot/actions.py
tiny_taskbot/bot.py
tiny_taskbot/scheduler.py
tiny_taskbot-1.0.0.dist-info/licenses/LICENSE
tiny_taskbot-1.0.0.dist-info/METADATA
tiny_taskbot-1.0.0.dist-info/WHEEL
tiny_taskbot-1.0.0.dist-info/entry_points.txt
tiny_taskbot-1.0.0.dist-info/top_level.txt
tiny_taskbot-1.0.0.dist-info/RECORD
