Metadata-Version: 2.4
Name: tiny-taskbot
Version: 1.0.0
Summary: A lightweight Python scheduler for timer and file-change tasks.
Home-page: https://gitlab.com/dmxsoftware/tiny-taskbot
Author: dmx3377
Author-email: david@dmx3377.uk
Project-URL: Homepage, https://tinytaskbot.dmx3377.uk/
Project-URL: Source, https://gitlab.com/dmxsoftware/tiny-taskbot
Project-URL: Documentation, https://gitlab.com/dmxsoftware/tiny-taskbot/README.md
Project-URL: Bug Tracker, https://gitlab.com/dmxsoftware/tiny-taskbot/-/issues
Classifier: Programming Language :: Python :: 3
Classifier: License :: OSI Approved :: BSD License
Classifier: Operating System :: OS Independent
Requires-Python: >=3.7
License-File: LICENSE
Requires-Dist: rich
Requires-Dist: watchdog
Requires-Dist: schedule
Requires-Dist: plyer
Dynamic: author
Dynamic: author-email
Dynamic: classifier
Dynamic: description
Dynamic: description-content-type
Dynamic: home-page
Dynamic: license-file
Dynamic: project-url
Dynamic: requires-dist
Dynamic: requires-python
Dynamic: summary
